AUTHORS
INSTALL
LICENSE
MANIFEST.in
README.rst
setup.py
doc/Makefile
doc/commands_api.rst
doc/conf.py
doc/customization.rst
doc/forms_api.rst
doc/getting_started.rst
doc/handlers.rst
doc/handlers_api.rst
doc/index.rst
doc/models_api.rst
doc/signals.rst
doc/templatetags_api.rst
doc/usage_examples.rst
doc/_static/TRACKME
ratings/__init__.py
ratings/admin.py
ratings/cookies.py
ratings/exceptions.py
ratings/handlers.py
ratings/managers.py
ratings/models.py
ratings/settings.py
ratings/signals.py
ratings/tests.py
ratings/urls.py
ratings/utils.py
ratings/forms/__init__.py
ratings/forms/widgets.py
ratings/management/__init__.py
ratings/management/commands/__init__.py
ratings/management/commands/upsert_scores.py
ratings/redsolution_setup/__init__.py
ratings/redsolution_setup/make.py
ratings/redsolution_setup/templates/settings.pyt
ratings/redsolution_setup/templates/urls.pyt
ratings/static/ratings/css/delete.gif
ratings/static/ratings/css/jquery.rating.css
ratings/static/ratings/css/star.gif
ratings/static/ratings/js/jquery.MetaData.js
ratings/static/ratings/js/jquery.rating.pack.js
ratings/static/ratings/js/ratings.js
ratings/templates/ratings/like_widget.html
ratings/templates/ratings/slider_widget.html
ratings/templates/ratings/star_widget.html
ratings/templatetags/__init__.py
ratings/templatetags/ratings_tags.py
ratings/views/__init__.py
ratings/views/generic.py
redsolutioncms.django_generic_ratings.egg-info/PKG-INFO
redsolutioncms.django_generic_ratings.egg-info/SOURCES.txt
redsolutioncms.django_generic_ratings.egg-info/dependency_links.txt
redsolutioncms.django_generic_ratings.egg-info/entry_points.txt
redsolutioncms.django_generic_ratings.egg-info/not-zip-safe
redsolutioncms.django_generic_ratings.egg-info/top_level.txt
tests/runtests.py
tests/settings.py