Metadata-Version: 1.0
Name: redsolutioncms.django-generic-ratings
Version: 0.6.1
Summary: This is our fork of original `Django-generic-ratings <http://pypi.python.org/pypi/django-generic-ratings/>`_ project. 
